partomatic/__init__.py
partomatic/automatable_part.py
partomatic/partomatic.py
partomatic/partomatic_config.py
partomatic-0.3.8.dist-info/METADATA
partomatic-0.3.8.dist-info/WHEEL
partomatic-0.3.8.dist-info/licenses/LICENSE
partomatic-0.3.8.dist-info/RECORD
