Metadata-Version: 2.4
Name: partomatic
Version: 0.3.8
Summary: build123d Part extended for CI/CD automation
Project-URL: Homepage, https://github.com/x0pherl/partomatic
Project-URL: Issues, https://github.com/x0pherl/partomatic/issues
Project-URL: Documentation, https://partomatic.readthedocs.org
Author: x0pherl
License-File: LICENSE
Classifier: License :: OSI Approved :: MIT License
Classifier: Operating System :: OS Independent
Classifier: Programming Language :: Python :: 3
Requires-Python: >=3.8
